setup.py
apize/__init__.py
apize/apize.py
apize/decorators.py
apize/exceptions.py
apize/http_request.py
apize.egg-info/PKG-INFO
apize.egg-info/SOURCES.txt
apize.egg-info/dependency_links.txt
apize.egg-info/requires.txt
apize.egg-info/top_level.txt