Metadata-Version: 1.1
Name: apize
Version: 0.2.2
Summary: Write quickly and easily to API clients
Home-page: http://github.com/herrersystem/apize
Author: herrersystem
Author-email: anton.millescamps@evhunter.fr
License: GNU General Public License (GPL)
Keywords: apize api client
Platform: UNKNOWN
Classifier: Development Status :: 5 - Production/Stable
Classifier: Intended Audience :: Developers
Classifier: License :: OSI Approved :: GNU General Public License (GPL)
Classifier: Topic :: Software Development
Classifier: Topic :: Software Development :: Libraries
Classifier: Programming Language :: Python
Classifier: Programming Language :: Python :: 3
Classifier: Programming Language :: Python :: 3.4
Classifier: Programming Language :: Python :: 3.5
